elk/__init__.py
elk/_version.py
elk/ensemble.py
elk/lightcurve.py
elk/plot.py
elk/stats.py
elk/utils.py
astro_elk-1.0.dist-info/METADATA
astro_elk-1.0.dist-info/WHEEL
astro_elk-1.0.dist-info/top_level.txt
astro_elk-1.0.dist-info/RECORD
