Metadata-Version: 2.1
Name: astro-elk
Version: 1.0
Summary: This python package computes, and corrects ensemble light curves for TESS pixels within a specified aperature, from TESS FFI data.
Home-page: https://github.com/tobin-wainer/TESS_Cluster_Project/
Author: Tobin Wainer, Tom Wagg
Author-email: tobinw@uw.edu
License: MIT
Platform: UNKNOWN
Provides: elk
Requires-Python: >=3.9
Requires-Dist: numpy <1.24
Requires-Dist: pip
Requires-Dist: matplotlib
Requires-Dist: astropy
Requires-Dist: scipy
Requires-Dist: jupyter
Requires-Dist: jupyterlab
Requires-Dist: ipython
Requires-Dist: pandas
Requires-Dist: tqdm
Requires-Dist: h5py
Requires-Dist: lightkurve ==2.4.0
Requires-Dist: tables
Requires-Dist: statsmodels
Requires-Dist: imageio
Provides-Extra: docs
Requires-Dist: sphinx ; extra == 'docs'
Requires-Dist: matplotlib ; extra == 'docs'
Provides-Extra: test
Requires-Dist: pytest ; extra == 'test'
